{
  "account": {
    "equity_usdt": 183.84601811569993,
    "open_positions": [],
    "realized_pnl_usdt": -24.37101504141884
  },
  "daily": {
    "consecutive_losses": 1,
    "daily_net_loss_limit_usdt": -2.7576902717354987,
    "daily_net_pnl_usdt": -1.2654747577120422,
    "daily_profit_stop_enabled": false,
    "date": "2026-06-27",
    "losses": 1,
    "stop_reason": null,
    "stop_trading_today": false,
    "trades_count": 1,
    "wins": 0
  },
  "errors": [],
  "mode": "live",
  "notifications": [],
  "rejects": [
    {
      "candidate_action": null,
      "reject_reason": "symbol_already_has_open_position",
      "symbol": "ETH-USDT-SWAP",
      "timestamp": "2026-06-27T11:31:07.949069+00:00"
    },
    {
      "candidate_action": null,
      "reject_reason": "symbol_already_has_open_position",
      "symbol": "ETH-USDT-SWAP",
      "timestamp": "2026-06-27T11:36:15.547127+00:00"
    },
    {
      "candidate_action": null,
      "reject_reason": "symbol_already_has_open_position",
      "symbol": "ETH-USDT-SWAP",
      "timestamp": "2026-06-27T11:41:16.913693+00:00"
    },
    {
      "candidate_action": null,
      "reject_reason": "symbol_already_has_open_position",
      "symbol": "ETH-USDT-SWAP",
      "timestamp": "2026-06-27T11:46:18.252720+00:00"
    },
    {
      "candidate_action": null,
      "reject_reason": "symbol_already_has_open_position",
      "symbol": "ETH-USDT-SWAP",
      "timestamp": "2026-06-27T11:51:18.902429+00:00"
    },
    {
      "candidate_action": null,
      "reject_reason": "symbol_already_has_open_position",
      "symbol": "ETH-USDT-SWAP",
      "timestamp": "2026-06-27T11:56:20.345934+00:00"
    },
    {
      "candidate_action": null,
      "reject_reason": "symbol_already_has_open_position",
      "symbol": "ETH-USDT-SWAP",
      "timestamp": "2026-06-27T12:01:20.994151+00:00"
    },
    {
      "candidate_action": null,
      "reject_reason": "symbol_already_has_open_position",
      "symbol": "ETH-USDT-SWAP",
      "timestamp": "2026-06-27T12:06:27.540308+00:00"
    },
    {
      "candidate_action": null,
      "reject_reason": "symbol_already_has_open_position",
      "symbol": "ETH-USDT-SWAP",
      "timestamp": "2026-06-27T12:11:28.142360+00:00"
    },
    {
      "candidate_action": null,
      "reject_reason": "symbol_already_has_open_position",
      "symbol": "ETH-USDT-SWAP",
      "timestamp": "2026-06-27T12:16:30.952603+00:00"
    },
    {
      "candidate_action": null,
      "reject_reason": "symbol_already_has_open_position",
      "symbol": "ETH-USDT-SWAP",
      "timestamp": "2026-06-27T12:21:31.527135+00:00"
    },
    {
      "candidate_action": null,
      "reject_reason": "symbol_already_has_open_position",
      "symbol": "ETH-USDT-SWAP",
      "timestamp": "2026-06-27T12:26:33.031912+00:00"
    },
    {
      "candidate_action": null,
      "reject_reason": "symbol_already_has_open_position",
      "symbol": "ETH-USDT-SWAP",
      "timestamp": "2026-06-27T12:31:34.012151+00:00"
    },
    {
      "candidate_action": null,
      "reject_reason": "symbol_already_has_open_position",
      "symbol": "ETH-USDT-SWAP",
      "timestamp": "2026-06-27T12:36:36.154774+00:00"
    },
    {
      "candidate_action": null,
      "reject_reason": "symbol_already_has_open_position",
      "symbol": "ETH-USDT-SWAP",
      "timestamp": "2026-06-27T12:41:36.795455+00:00"
    },
    {
      "candidate_action": null,
      "reject_reason": "symbol_already_has_open_position",
      "symbol": "ETH-USDT-SWAP",
      "timestamp": "2026-06-27T12:46:38.709301+00:00"
    },
    {
      "candidate_action": null,
      "reject_reason": "symbol_already_has_open_position",
      "symbol": "ETH-USDT-SWAP",
      "timestamp": "2026-06-27T12:51:39.768442+00:00"
    },
    {
      "candidate_action": null,
      "reject_reason": "symbol_already_has_open_position",
      "symbol": "ETH-USDT-SWAP",
      "timestamp": "2026-06-27T12:56:41.606213+00:00"
    },
    {
      "candidate_action": null,
      "reject_reason": "symbol_already_has_open_position",
      "symbol": "ETH-USDT-SWAP",
      "timestamp": "2026-06-27T13:01:47.229177+00:00"
    },
    {
      "candidate_action": null,
      "reject_reason": "symbol_already_has_open_position",
      "symbol": "ETH-USDT-SWAP",
      "timestamp": "2026-06-27T13:06:48.722479+00:00"
    },
    {
      "candidate_action": null,
      "reject_reason": "symbol_already_has_open_position",
      "symbol": "ETH-USDT-SWAP",
      "timestamp": "2026-06-27T13:11:55.306797+00:00"
    },
    {
      "candidate_action": null,
      "reject_reason": "symbol_already_has_open_position",
      "symbol": "ETH-USDT-SWAP",
      "timestamp": "2026-06-27T13:17:03.037306+00:00"
    },
    {
      "candidate_action": null,
      "reject_reason": "symbol_already_has_open_position",
      "symbol": "ETH-USDT-SWAP",
      "timestamp": "2026-06-27T13:22:03.735112+00:00"
    },
    {
      "candidate_action": null,
      "reject_reason": "symbol_already_has_open_position",
      "symbol": "ETH-USDT-SWAP",
      "timestamp": "2026-06-27T13:27:05.172390+00:00"
    },
    {
      "candidate_action": null,
      "reject_reason": "symbol_already_has_open_position",
      "symbol": "ETH-USDT-SWAP",
      "timestamp": "2026-06-27T13:32:05.843057+00:00"
    },
    {
      "candidate_action": null,
      "reject_reason": "symbol_already_has_open_position",
      "symbol": "ETH-USDT-SWAP",
      "timestamp": "2026-06-27T13:37:07.374853+00:00"
    },
    {
      "candidate_action": null,
      "reject_reason": "symbol_already_has_open_position",
      "symbol": "ETH-USDT-SWAP",
      "timestamp": "2026-06-27T13:42:13.169400+00:00"
    },
    {
      "candidate_action": null,
      "reject_reason": "symbol_already_has_open_position",
      "symbol": "ETH-USDT-SWAP",
      "timestamp": "2026-06-27T13:47:14.817279+00:00"
    },
    {
      "candidate_action": null,
      "reject_reason": "symbol_already_has_open_position",
      "symbol": "ETH-USDT-SWAP",
      "timestamp": "2026-06-27T13:52:15.513400+00:00"
    },
    {
      "candidate_action": null,
      "reject_reason": "no_rule_candidate",
      "symbol": "ETH-USDT-SWAP",
      "timestamp": "2026-06-27T13:57:20.233011+00:00"
    }
  ],
  "service": {
    "dashboard": "active",
    "live": "active",
    "paper": "inactive"
  },
  "signals": [],
  "snapshot_policy": {
    "kind": "public_sanitized",
    "redaction": "raw exchange payloads, order responses, error bodies, notification responses, and credentials are excluded",
    "update_interval_minutes": 15
  },
  "strategy_stats": {
    "by_regime": {
      "bearish_trend": {
        "avg_loss_usdt": -1.4711920834102072,
        "avg_win_usdt": 1.6815087667342876,
        "closed_trades": 17,
        "gross_loss_usdt": -16.18311292,
        "gross_win_usdt": 10.0890526,
        "losses": 11,
        "net_pnl_usdt": -6.09406032,
        "win_rate": 0.35294117647058826,
        "wins": 6
      },
      "bullish_trend": {
        "avg_loss_usdt": -1.2864111617083136,
        "avg_win_usdt": 1.3994263807051304,
        "closed_trades": 9,
        "gross_loss_usdt": -10.29128929,
        "gross_win_usdt": 1.39942638,
        "losses": 8,
        "net_pnl_usdt": -8.89186291,
        "win_rate": 0.1111111111111111,
        "wins": 1
      },
      "range": {
        "avg_loss_usdt": -1.589635282133273,
        "avg_win_usdt": 1.7423551635819985,
        "closed_trades": 8,
        "gross_loss_usdt": -11.12744697,
        "gross_win_usdt": 1.74235516,
        "losses": 7,
        "net_pnl_usdt": -9.38509181,
        "win_rate": 0.125,
        "wins": 1
      }
    },
    "by_strategy": {
      "range_reversal": {
        "avg_loss_usdt": -1.589635282133273,
        "avg_win_usdt": 1.7423551635819985,
        "closed_trades": 8,
        "gross_loss_usdt": -11.12744697,
        "gross_win_usdt": 1.74235516,
        "losses": 7,
        "net_pnl_usdt": -9.38509181,
        "win_rate": 0.125,
        "wins": 1
      },
      "trend_momentum": {
        "avg_loss_usdt": -1.3914439092781,
        "avg_win_usdt": 0.0,
        "closed_trades": 5,
        "gross_loss_usdt": -6.95721955,
        "gross_win_usdt": 0.0,
        "losses": 5,
        "net_pnl_usdt": -6.95721955,
        "win_rate": 0.0,
        "wins": 0
      },
      "trend_pullback": {
        "avg_loss_usdt": -1.3884806791888489,
        "avg_win_usdt": 1.6805770261825366,
        "closed_trades": 19,
        "gross_loss_usdt": -18.05024883,
        "gross_win_usdt": 10.08346216,
        "losses": 13,
        "net_pnl_usdt": -7.96678667,
        "win_rate": 0.3157894736842105,
        "wins": 6
      },
      "unknown": {
        "avg_loss_usdt": -1.4669338353332517,
        "avg_win_usdt": 1.4050168240156375,
        "closed_trades": 2,
        "gross_loss_usdt": -1.46693384,
        "gross_win_usdt": 1.40501682,
        "losses": 1,
        "net_pnl_usdt": -0.06191701,
        "win_rate": 0.5,
        "wins": 1
      }
    },
    "by_symbol": {
      "BTC-USDT-SWAP": {
        "avg_loss_usdt": -1.1884146899253356,
        "avg_win_usdt": 1.2513404940855501,
        "closed_trades": 8,
        "gross_loss_usdt": -8.31890283,
        "gross_win_usdt": 1.25134049,
        "losses": 7,
        "net_pnl_usdt": -7.06756234,
        "win_rate": 0.125,
        "wins": 1
      },
      "ETH-USDT-SWAP": {
        "avg_loss_usdt": -1.5412077029807552,
        "avg_win_usdt": 1.7113562358010432,
        "closed_trades": 26,
        "gross_loss_usdt": -29.28294636,
        "gross_win_usdt": 11.97949365,
        "losses": 19,
        "net_pnl_usdt": -17.30345271,
        "win_rate": 0.2692307692307692,
        "wins": 7
      }
    }
  },
  "symbols": [
    "ETH-USDT-SWAP"
  ],
  "timestamp": "2026-06-27T14:00:16.264412+00:00",
  "trades": [
    {
      "event": "CLOSE",
      "exit_reason": "exchange_tpsl_closed",
      "net_pnl_usdt": -1.240140217797337,
      "notional_usdt": 0.0,
      "price": 1731.1,
      "rule_market_regime": "bullish_trend",
      "side": "SELL",
      "strategy_mode": "trend_momentum",
      "symbol": "ETH-USDT-SWAP",
      "timestamp": "2026-06-20T16:32:19.416591+00:00"
    },
    {
      "event": "OPEN",
      "exit_reason": null,
      "net_pnl_usdt": 0.0,
      "notional_usdt": 200.0,
      "price": 1731.08,
      "rule_market_regime": "bullish_trend",
      "side": "LONG",
      "strategy_mode": "trend_pullback",
      "symbol": "ETH-USDT-SWAP",
      "timestamp": "2026-06-20T16:32:25.769469+00:00"
    },
    {
      "event": "CLOSE",
      "exit_reason": "exchange_tpsl_closed",
      "net_pnl_usdt": -0.8469949395752836,
      "notional_usdt": 0.0,
      "price": 1725.48,
      "rule_market_regime": "bullish_trend",
      "side": "SELL",
      "strategy_mode": "trend_pullback",
      "symbol": "ETH-USDT-SWAP",
      "timestamp": "2026-06-20T17:42:56.913524+00:00"
    },
    {
      "event": "OPEN",
      "exit_reason": null,
      "net_pnl_usdt": 0.0,
      "notional_usdt": 200.0,
      "price": 1729.37,
      "rule_market_regime": "bullish_trend",
      "side": "LONG",
      "strategy_mode": "trend_pullback",
      "symbol": "ETH-USDT-SWAP",
      "timestamp": "2026-06-20T18:03:14.396231+00:00"
    },
    {
      "event": "CLOSE",
      "exit_reason": "exchange_tpsl_closed",
      "net_pnl_usdt": 1.3994263807051304,
      "notional_usdt": 0.0,
      "price": 1743.2,
      "rule_market_regime": "bullish_trend",
      "side": "SELL",
      "strategy_mode": "trend_pullback",
      "symbol": "ETH-USDT-SWAP",
      "timestamp": "2026-06-20T22:36:10.466804+00:00"
    },
    {
      "event": "OPEN",
      "exit_reason": null,
      "net_pnl_usdt": 0.0,
      "notional_usdt": 200.0,
      "price": 1740.06,
      "rule_market_regime": "bullish_trend",
      "side": "LONG",
      "strategy_mode": "trend_momentum",
      "symbol": "ETH-USDT-SWAP",
      "timestamp": "2026-06-20T23:32:39.269765+00:00"
    },
    {
      "event": "CLOSE",
      "exit_reason": "exchange_tpsl_closed",
      "net_pnl_usdt": -1.096520809627249,
      "notional_usdt": 0.0,
      "price": 1732.26,
      "rule_market_regime": "bullish_trend",
      "side": "SELL",
      "strategy_mode": "trend_momentum",
      "symbol": "ETH-USDT-SWAP",
      "timestamp": "2026-06-21T05:00:19.246543+00:00"
    },
    {
      "event": "OPEN",
      "exit_reason": null,
      "net_pnl_usdt": 0.0,
      "notional_usdt": 200.0,
      "price": 1735.0,
      "rule_market_regime": "bullish_trend",
      "side": "LONG",
      "strategy_mode": "trend_pullback",
      "symbol": "ETH-USDT-SWAP",
      "timestamp": "2026-06-21T06:32:33.492221+00:00"
    },
    {
      "event": "CLOSE",
      "exit_reason": "exchange_tpsl_closed",
      "net_pnl_usdt": -1.1844380403458172,
      "notional_usdt": 0.0,
      "price": 1726.46,
      "rule_market_regime": "bullish_trend",
      "side": "SELL",
      "strategy_mode": "trend_pullback",
      "symbol": "ETH-USDT-SWAP",
      "timestamp": "2026-06-21T08:43:46.926698+00:00"
    },
    {
      "event": "OPEN",
      "exit_reason": null,
      "net_pnl_usdt": 0.0,
      "notional_usdt": 200.0,
      "price": 1734.48,
      "rule_market_regime": "bullish_trend",
      "side": "LONG",
      "strategy_mode": "trend_pullback",
      "symbol": "ETH-USDT-SWAP",
      "timestamp": "2026-06-21T19:32:10.524300+00:00"
    },
    {
      "event": "CLOSE",
      "exit_reason": "exchange_tpsl_closed",
      "net_pnl_usdt": -1.2124071767907352,
      "notional_usdt": 0.0,
      "price": 1725.7,
      "rule_market_regime": "bullish_trend",
      "side": "SELL",
      "strategy_mode": "trend_pullback",
      "symbol": "ETH-USDT-SWAP",
      "timestamp": "2026-06-21T20:42:09.170853+00:00"
    },
    {
      "event": "CLOSE",
      "exit_reason": "exchange_tpsl_closed",
      "net_pnl_usdt": -1.102536098319894,
      "notional_usdt": 0.0,
      "price": 63730.7,
      "rule_market_regime": "bullish_trend",
      "side": "SELL",
      "strategy_mode": "trend_pullback",
      "symbol": "BTC-USDT-SWAP",
      "timestamp": "2026-06-21T20:52:16.567379+00:00"
    },
    {
      "event": "OPEN",
      "exit_reason": null,
      "net_pnl_usdt": 0.0,
      "notional_usdt": 200.0,
      "price": 1745.0,
      "rule_market_regime": "bullish_trend",
      "side": "LONG",
      "strategy_mode": "trend_momentum",
      "symbol": "ETH-USDT-SWAP",
      "timestamp": "2026-06-22T01:56:35.231409+00:00"
    },
    {
      "event": "OPEN",
      "exit_reason": null,
      "net_pnl_usdt": 0.0,
      "notional_usdt": 200.0,
      "price": 64548.8,
      "rule_market_regime": "bullish_trend",
      "side": "LONG",
      "strategy_mode": "trend_momentum",
      "symbol": "BTC-USDT-SWAP",
      "timestamp": "2026-06-22T02:16:59.728300+00:00"
    },
    {
      "event": "CLOSE",
      "exit_reason": "exchange_tpsl_closed",
      "net_pnl_usdt": -1.8779369627507276,
      "notional_usdt": 0.0,
      "price": 1730.36,
      "rule_market_regime": "bullish_trend",
      "side": "SELL",
      "strategy_mode": "trend_momentum",
      "symbol": "ETH-USDT-SWAP",
      "timestamp": "2026-06-22T03:06:53.214433+00:00"
    },
    {
      "event": "CLOSE",
      "exit_reason": "exchange_tpsl_closed",
      "net_pnl_usdt": -1.7303150484594645,
      "notional_usdt": 0.0,
      "price": 64054.9,
      "rule_market_regime": "bullish_trend",
      "side": "SELL",
      "strategy_mode": "trend_momentum",
      "symbol": "BTC-USDT-SWAP",
      "timestamp": "2026-06-22T03:06:53.536705+00:00"
    },
    {
      "event": "OPEN",
      "exit_reason": null,
      "net_pnl_usdt": 0.0,
      "notional_usdt": 150.0,
      "price": 1659.91,
      "rule_market_regime": "bearish_trend",
      "side": "SHORT",
      "strategy_mode": "trend_pullback",
      "symbol": "ETH-USDT-SWAP",
      "timestamp": "2026-06-23T11:25:45.381230+00:00"
    },
    {
      "event": "CLOSE",
      "exit_reason": "exchange_tpsl_closed",
      "net_pnl_usdt": -1.6139347916453135,
      "notional_usdt": 0.0,
      "price": 1676.11,
      "rule_market_regime": "bearish_trend",
      "side": "BUY",
      "strategy_mode": "trend_pullback",
      "symbol": "ETH-USDT-SWAP",
      "timestamp": "2026-06-24T01:39:41.341451+00:00"
    },
    {
      "event": "OPEN",
      "exit_reason": null,
      "net_pnl_usdt": 0.0,
      "notional_usdt": 150.0,
      "price": 1659.29,
      "rule_market_regime": "range",
      "side": "LONG",
      "strategy_mode": "range_reversal",
      "symbol": "ETH-USDT-SWAP",
      "timestamp": "2026-06-24T04:31:14.147097+00:00"
    },
    {
      "event": "CLOSE",
      "exit_reason": "exchange_tpsl_closed",
      "net_pnl_usdt": -1.8025140270838709,
      "notional_usdt": 0.0,
      "price": 1641.01,
      "rule_market_regime": "range",
      "side": "SELL",
      "strategy_mode": "range_reversal",
      "symbol": "ETH-USDT-SWAP",
      "timestamp": "2026-06-24T15:11:52.335526+00:00"
    },
    {
      "event": "OPEN",
      "exit_reason": null,
      "net_pnl_usdt": 0.0,
      "notional_usdt": 150.0,
      "price": 1615.18,
      "rule_market_regime": "bearish_trend",
      "side": "SHORT",
      "strategy_mode": "trend_pullback",
      "symbol": "ETH-USDT-SWAP",
      "timestamp": "2026-06-25T02:13:56.240943+00:00"
    },
    {
      "event": "CLOSE",
      "exit_reason": "exchange_tpsl_closed",
      "net_pnl_usdt": -1.9302969328495752,
      "notional_usdt": 0.0,
      "price": 1634.35,
      "rule_market_regime": "bearish_trend",
      "side": "BUY",
      "strategy_mode": "trend_pullback",
      "symbol": "ETH-USDT-SWAP",
      "timestamp": "2026-06-25T04:59:37.393188+00:00"
    },
    {
      "event": "OPEN",
      "exit_reason": null,
      "net_pnl_usdt": 0.0,
      "notional_usdt": 150.0,
      "price": 1644.05,
      "rule_market_regime": "range",
      "side": "SHORT",
      "strategy_mode": "range_reversal",
      "symbol": "ETH-USDT-SWAP",
      "timestamp": "2026-06-25T06:05:22.577048+00:00"
    },
    {
      "event": "CLOSE",
      "exit_reason": "exchange_tpsl_closed",
      "net_pnl_usdt": -0.8990648094644357,
      "notional_usdt": 0.0,
      "price": 1652.26,
      "rule_market_regime": "range",
      "side": "BUY",
      "strategy_mode": "range_reversal",
      "symbol": "ETH-USDT-SWAP",
      "timestamp": "2026-06-25T07:00:44.336429+00:00"
    },
    {
      "event": "OPEN",
      "exit_reason": null,
      "net_pnl_usdt": 0.0,
      "notional_usdt": 150.0,
      "price": 1631.41,
      "rule_market_regime": "range",
      "side": "LONG",
      "strategy_mode": "range_reversal",
      "symbol": "ETH-USDT-SWAP",
      "timestamp": "2026-06-25T11:48:24.035035+00:00"
    },
    {
      "event": "CLOSE",
      "exit_reason": "exchange_tpsl_closed",
      "net_pnl_usdt": -3.538173420538074,
      "notional_usdt": 0.0,
      "price": 1594.56,
      "rule_market_regime": "range",
      "side": "SELL",
      "strategy_mode": "range_reversal",
      "symbol": "ETH-USDT-SWAP",
      "timestamp": "2026-06-25T13:43:56.276743+00:00"
    },
    {
      "event": "OPEN",
      "exit_reason": null,
      "net_pnl_usdt": 0.0,
      "notional_usdt": 150.0,
      "price": 1568.72,
      "rule_market_regime": "bearish_trend",
      "side": "SHORT",
      "strategy_mode": "trend_pullback",
      "symbol": "ETH-USDT-SWAP",
      "timestamp": "2026-06-26T00:02:47.609295+00:00"
    },
    {
      "event": "CLOSE",
      "exit_reason": "exchange_tpsl_closed",
      "net_pnl_usdt": 3.4299887806619465,
      "notional_usdt": 0.0,
      "price": 1531.28,
      "rule_market_regime": "bearish_trend",
      "side": "BUY",
      "strategy_mode": "trend_pullback",
      "symbol": "ETH-USDT-SWAP",
      "timestamp": "2026-06-26T02:18:22.425357+00:00"
    },
    {
      "event": "OPEN",
      "exit_reason": null,
      "net_pnl_usdt": 0.0,
      "notional_usdt": 150.0,
      "price": 1547.1,
      "rule_market_regime": "bearish_trend",
      "side": "SHORT",
      "strategy_mode": "trend_pullback",
      "symbol": "ETH-USDT-SWAP",
      "timestamp": "2026-06-26T03:49:03.693806+00:00"
    },
    {
      "event": "CLOSE",
      "exit_reason": "exchange_tpsl_closed",
      "net_pnl_usdt": -0.9809094434749045,
      "notional_usdt": 0.0,
      "price": 1555.67,
      "rule_market_regime": "bearish_trend",
      "side": "BUY",
      "strategy_mode": "trend_pullback",
      "symbol": "ETH-USDT-SWAP",
      "timestamp": "2026-06-26T03:59:10.157626+00:00"
    },
    {
      "event": "OPEN",
      "exit_reason": null,
      "net_pnl_usdt": 0.0,
      "notional_usdt": 150.0,
      "price": 1548.12,
      "rule_market_regime": "bearish_trend",
      "side": "SHORT",
      "strategy_mode": "trend_pullback",
      "symbol": "ETH-USDT-SWAP",
      "timestamp": "2026-06-26T04:55:21.091693+00:00"
    },
    {
      "event": "CLOSE",
      "exit_reason": "exchange_tpsl_closed",
      "net_pnl_usdt": -1.7835942950159025,
      "notional_usdt": 0.0,
      "price": 1564.98,
      "rule_market_regime": "bearish_trend",
      "side": "BUY",
      "strategy_mode": "trend_pullback",
      "symbol": "ETH-USDT-SWAP",
      "timestamp": "2026-06-26T06:41:33.085783+00:00"
    },
    {
      "event": "OPEN",
      "exit_reason": null,
      "net_pnl_usdt": 0.0,
      "notional_usdt": 150.0,
      "price": 1569.25,
      "rule_market_regime": "range",
      "side": "SHORT",
      "strategy_mode": "range_reversal",
      "symbol": "ETH-USDT-SWAP",
      "timestamp": "2026-06-26T06:53:44.896523+00:00"
    },
    {
      "event": "CLOSE",
      "exit_reason": "exchange_tpsl_closed",
      "net_pnl_usdt": -1.3180739206627394,
      "notional_usdt": 0.0,
      "price": 1581.47,
      "rule_market_regime": "range",
      "side": "BUY",
      "strategy_mode": "range_reversal",
      "symbol": "ETH-USDT-SWAP",
      "timestamp": "2026-06-26T07:32:03.133585+00:00"
    },
    {
      "event": "OPEN",
      "exit_reason": null,
      "net_pnl_usdt": 0.0,
      "notional_usdt": 150.0,
      "price": 1564.13,
      "rule_market_regime": "bearish_trend",
      "side": "SHORT",
      "strategy_mode": "trend_pullback",
      "symbol": "ETH-USDT-SWAP",
      "timestamp": "2026-06-26T08:55:08.074037+00:00"
    },
    {
      "event": "CLOSE",
      "exit_reason": "exchange_tpsl_closed",
      "net_pnl_usdt": 2.031724025496602,
      "notional_usdt": 0.0,
      "price": 1541.38,
      "rule_market_regime": "bearish_trend",
      "side": "BUY",
      "strategy_mode": "trend_pullback",
      "symbol": "ETH-USDT-SWAP",
      "timestamp": "2026-06-26T11:54:14.100764+00:00"
    },
    {
      "event": "OPEN",
      "exit_reason": null,
      "net_pnl_usdt": 0.0,
      "notional_usdt": 150.0,
      "price": 1537.92,
      "rule_market_regime": "bearish_trend",
      "side": "SHORT",
      "strategy_mode": "trend_pullback",
      "symbol": "ETH-USDT-SWAP",
      "timestamp": "2026-06-26T13:32:04.528464+00:00"
    },
    {
      "event": "CLOSE",
      "exit_reason": "exchange_tpsl_closed",
      "net_pnl_usdt": -2.6341994382022493,
      "notional_usdt": 0.0,
      "price": 1563.39,
      "rule_market_regime": "bearish_trend",
      "side": "BUY",
      "strategy_mode": "trend_pullback",
      "symbol": "ETH-USDT-SWAP",
      "timestamp": "2026-06-26T13:55:23.216146+00:00"
    },
    {
      "event": "OPEN",
      "exit_reason": null,
      "net_pnl_usdt": 0.0,
      "notional_usdt": 150.0,
      "price": 1578.7,
      "rule_market_regime": "range",
      "side": "SHORT",
      "strategy_mode": "range_reversal",
      "symbol": "ETH-USDT-SWAP",
      "timestamp": "2026-06-26T16:13:41.915579+00:00"
    },
    {
      "event": "CLOSE",
      "exit_reason": "exchange_tpsl_closed",
      "net_pnl_usdt": -1.2654747577120422,
      "notional_usdt": 0.0,
      "price": 1590.44,
      "rule_market_regime": "range",
      "side": "BUY",
      "strategy_mode": "range_reversal",
      "symbol": "ETH-USDT-SWAP",
      "timestamp": "2026-06-27T13:55:17.419195+00:00"
    }
  ]
}
